README.txt
setup.cfg
setup.py
twill-fork
quokka_twill.egg-info/PKG-INFO
quokka_twill.egg-info/SOURCES.txt
quokka_twill.egg-info/dependency_links.txt
quokka_twill.egg-info/entry_points.txt
quokka_twill.egg-info/top_level.txt
twill/__init__.py
twill/browser.py
twill/commands.py
twill/errors.py
twill/namespaces.py
twill/parse.py
twill/shell.py
twill/unit.py
twill/utils.py
twill/wsgi_intercept.py
twill/extensions/__init__.py
twill/extensions/argparse.py
twill/extensions/check_links.py
twill/extensions/csv_iterate.py
twill/extensions/dirstack.py
twill/extensions/dns_check.py
twill/extensions/formfill.py
twill/extensions/mailman_sf.py
twill/extensions/require.py
twill/extensions/test_extensions.py
twill/extensions/match_parse/__init__.py
twill/extensions/match_parse/test-match_parse.py
twill/other_packages/__init__.py
twill/other_packages/pyparsing.py
twill/other_packages/subprocess.py
twill/other_packages/_mechanize_dist/ClientForm.py
twill/other_packages/_mechanize_dist/__init__.py
twill/other_packages/_mechanize_dist/_auth.py
twill/other_packages/_mechanize_dist/_beautifulsoup.py
twill/other_packages/_mechanize_dist/_clientcookie.py
twill/other_packages/_mechanize_dist/_debug.py
twill/other_packages/_mechanize_dist/_gzip.py
twill/other_packages/_mechanize_dist/_headersutil.py
twill/other_packages/_mechanize_dist/_html.py
twill/other_packages/_mechanize_dist/_http.py
twill/other_packages/_mechanize_dist/_lwpcookiejar.py
twill/other_packages/_mechanize_dist/_mechanize.py
twill/other_packages/_mechanize_dist/_mozillacookiejar.py
twill/other_packages/_mechanize_dist/_msiecookiejar.py
twill/other_packages/_mechanize_dist/_opener.py
twill/other_packages/_mechanize_dist/_pullparser.py
twill/other_packages/_mechanize_dist/_request.py
twill/other_packages/_mechanize_dist/_response.py
twill/other_packages/_mechanize_dist/_rfc3986.py
twill/other_packages/_mechanize_dist/_seek.py
twill/other_packages/_mechanize_dist/_upgrade.py
twill/other_packages/_mechanize_dist/_urllib2.py
twill/other_packages/_mechanize_dist/_useragent.py
twill/other_packages/_mechanize_dist/_util.py