Metadata-Version: 1.1
Name: quokka-twill
Version: 1.8.0
Summary: fork of twill Web browsing language
Home-page: http://twill.idyll.org/
Author: C. Titus Brown
Author-email: titus@idyll.org
License: MIT
Platform: UNKNOWN
Classifier: Development Status :: 4 - Beta
Classifier: Environment :: Console
Classifier: Intended Audience :: Developers
Classifier: Intended Audience :: System Administrators
Classifier: License :: OSI Approved :: MIT License
Classifier: Natural Language :: English
Classifier: Operating System :: OS Independent
Classifier: Programming Language :: Python
Classifier: Programming Language :: Other Scripting Engines
Classifier: Topic :: Internet :: WWW/HTTP
Classifier: Topic :: Software Development :: Testing
